mcp_test_020402_2/__init__.py
mcp_test_020402_2/server.py
mcp_test_020402_2-0.1.0.dist-info/METADATA
mcp_test_020402_2-0.1.0.dist-info/WHEEL
mcp_test_020402_2-0.1.0.dist-info/entry_points.txt
mcp_test_020402_2-0.1.0.dist-info/RECORD
