Metadata-Version: 2.4
Name: mcp-test-020402-2
Version: 0.1.0
Summary: Add your description here
Requires-Python: >=3.11
Requires-Dist: beautifulsoup4>=4.14.3
Requires-Dist: build>=1.3.0
Requires-Dist: mcp[cli]>=1.24.0
Requires-Dist: requests>=2.32.5
Requires-Dist: twine>=6.2.0
